LICENSE.txt
MANIFEST.in
README.md
setup.cfg
setup.py
brilws/RegexValidator.py
brilws/__init__.py
brilws/_version.py
brilws/api.py
brilws/corrector.py
brilws/display.py
brilws/fileapi.py
brilws/formatter.py
brilws/lumiParameters.py
brilws/params.py
brilws/timeconvert.py
brilws.egg-info/PKG-INFO
brilws.egg-info/SOURCES.txt
brilws.egg-info/dependency_links.txt
brilws.egg-info/entry_points.txt
brilws.egg-info/top_level.txt
brilws/cli/__init__.py
brilws/cli/brilcalc_beam.py
brilws/cli/brilcalc_lumi.py
brilws/cli/brilcalc_main.py
brilws/cli/brilcalc_trg.py
brilws/cli/brilschema_create.py
brilws/cli/brilschema_loaddata.py
brilws/cli/brilschema_loadmap.py
brilws/cli/brilschema_loadresult.py
brilws/cli/brilschema_main.py
brilws/cli/briltag_insertdata.py
brilws/cli/briltag_insertiov.py
brilws/cli/briltag_listdata.py
brilws/cli/briltag_listiov.py
brilws/cli/briltag_main.py
brilws/cli/clicommonargs.py
brilws/data/__init__.py
brilws/data/bcm1fv1.yaml
brilws/data/readdb3.ini
brilws/dbschema/__init__.py
brilws/dbschema/schema_fixed.yaml
brilws/dbschema/schema_iov.yaml
brilws/dbschema/schema_sharded.yaml
brilws/dbschema/schema_trg.yaml