Metadata-Version: 2.1
Name: brilws
Version: 3.8.1
Summary: bril worksuite
Home-page: https://github.com/xiezhen/brilws
Download-URL: https://github.com/xiezhen/brilws/tarball/3.8.1
Author: Zhen Xie
License: MIT
License-File: LICENSE.txt
